dota2_random_hero/__init__.py
dota2_random_hero/heroes.py
dota2_random_hero/random_hero.py
dota_random_hero-0.1.1.dist-info/METADATA
dota_random_hero-0.1.1.dist-info/WHEEL
dota_random_hero-0.1.1.dist-info/top_level.txt
dota_random_hero-0.1.1.dist-info/RECORD
